[
  {
    "date": "2024-12-31",
    "symbol": "IBM",
    "reportedCurrency": "USD",
    "cik": "0000051143",
    "filingDate": "2025-02-25",
    "acceptedDate": "2025-02-25 16:12:45",
    "fiscalYear": "2024",
    "period": "FY",
    "cashAndCashEquivalents": 13947000000,
    "shortTermInvestments": 644000000,
    "cashAndShortTermInvestments": 14591000000,
    "netReceivables": 14010000000,
    "accountsReceivables": 6804000000,
    "otherReceivables": 8106000000,
    "inventory": 1289000000,
    "prepaids": 2476000000,
    "otherCurrentAssets": 2116000000,
    "totalCurrentAssets": 34482000000,
    "propertyPlantEquipmentNet": 8928000000,
    "goodwill": 60706000000,
    "intangibleAssets": 10660000000,
    "goodwillAndIntangibleAssets": 71366000000,
    "longTermInvestments": 1787000000,
    "taxAssets": 1000000,
    "otherNonCurrentAssets": 20612000000,
    "totalNonCurrentAssets": 102694000000,
    "otherAssets": -1000000,
    "totalAssets": 137175000000,
    "totalPayables": 6065000000,
    "accountPayables": 4032000000,
    "otherPayables": 2033000000,
    "accruedExpenses": 3605000000,
    "shortTermDebt": 5089000000,
    "capitalLeaseObligationsCurrent": 768000000,
    "taxPayables": 2033000000,
    "deferredRevenue": 13907000000,
    "otherCurrentLiabilities": 3708000000,
    "totalCurrentLiabilities": 33142000000,
    "longTermDebt": 49884000000,
    "capitalLeaseObligationsNonCurrent": 2655000000,
    "deferredRevenueNonCurrent": 0,
    "deferredTaxLiabilitiesNonCurrent": 0,
    "otherNonCurrentLiabilities": 24101000000,
    "totalNonCurrentLiabilities": 76640000000,
    "otherLiabilities": 0,
    "capitalLeaseObligations": 3423000000,
    "totalLiabilities": 109782000000,
    "treasuryStock": -169968000000,
    "preferredStock": 0,
    "commonStock": 61380000000,
    "retainedEarnings": 151163000000,
    "additionalPaidInCapital": 0,
    "accumulatedOtherComprehensiveIncomeLoss": -15269000000,
    "otherTotalStockholdersEquity": 1000000,
    "totalStockholdersEquity": 27307000000,
    "totalEquity": 27393000000,
    "minorityInterest": 86000000,
    "totalLiabilitiesAndTotalEquity": 137175000000,
    "totalInvestments": 2431000000,
    "totalDebt": 58396000000,
    "netDebt": 44449000000
  },
  {
    "date": "2023-12-31",
    "symbol": "IBM",
    "reportedCurrency": "USD",
    "cik": "0000051143",
    "filingDate": "2024-02-26",
    "acceptedDate": "2024-02-26 06:41:57",
    "fiscalYear": "2023",
    "period": "FY",
    "cashAndCashEquivalents": 13068000000,
    "shortTermInvestments": 373000000,
    "cashAndShortTermInvestments": 13441000000,
    "netReceivables": 7719000000,
    "accountsReceivables": 7214000000,
    "otherReceivables": 640000000,
    "inventory": 1161000000,
    "prepaids": 1768000000,
    "otherCurrentAssets": 8819000000,
    "totalCurrentAssets": 32908000000,
    "propertyPlantEquipmentNet": 8721000000,
    "goodwill": 60178000000,
    "intangibleAssets": 11036000000,
    "goodwillAndIntangibleAssets": 71214000000,
    "longTermInvestments": 5961000000,
    "taxAssets": 6656000000,
    "otherNonCurrentAssets": 9781000000,
    "totalNonCurrentAssets": 102333000000,
    "otherAssets": 0,
    "totalAssets": 135241000000,
    "totalPayables": 6402000000,
    "accountPayables": 4132000000,
    "otherPayables": 2270000000,
    "accruedExpenses": 3501000000,
    "shortTermDebt": 6426000000,
    "capitalLeaseObligationsCurrent": 820000000,
    "taxPayables": 2270000000,
    "deferredRevenue": 13451000000,
    "otherCurrentLiabilities": 3522000000,
    "totalCurrentLiabilities": 34122000000,
    "longTermDebt": 49767000000,
    "capitalLeaseObligationsNonCurrent": 2922000000,
    "deferredRevenueNonCurrent": 3533000000,
    "deferredTaxLiabilitiesNonCurrent": 1146000000,
    "otherNonCurrentLiabilities": 21138000000,
    "totalNonCurrentLiabilities": 78506000000,
    "otherLiabilities": 0,
    "capitalLeaseObligations": 3388000000,
    "totalLiabilities": 112628000000,
    "treasuryStock": -169625000000,
    "preferredStock": 0,
    "commonStock": 59643000000,
    "retainedEarnings": 151276000000,
    "additionalPaidInCapital": 0,
    "accumulatedOtherComprehensiveIncomeLoss": -18761000000,
    "otherTotalStockholdersEquity": 0,
    "totalStockholdersEquity": 22533000000,
    "totalEquity": 22613000000,
    "minorityInterest": 80000000,
    "totalLiabilitiesAndTotalEquity": 135241000000,
    "totalInvestments": 6334000000,
    "totalDebt": 59935000000,
    "netDebt": 46867000000
  },
  {
    "date": "2022-12-31",
    "symbol": "IBM",
    "reportedCurrency": "USD",
    "cik": "0000051143",
    "filingDate": "2023-02-28",
    "acceptedDate": "2023-02-28 16:26:11",
    "fiscalYear": "2022",
    "period": "FY",
    "cashAndCashEquivalents": 7886000000,
    "shortTermInvestments": 852000000,
    "cashAndShortTermInvestments": 8738000000,
    "netReceivables": 7005000000,
    "accountsReceivables": 6541000000,
    "otherReceivables": 464000000,
    "inventory": 1552000000,
    "prepaids": 1876000000,
    "otherCurrentAssets": 9947000000,
    "totalCurrentAssets": 29118000000,
    "propertyPlantEquipmentNet": 8212000000,
    "goodwill": 55949000000,
    "intangibleAssets": 11184000000,
    "goodwillAndIntangibleAssets": 67133000000,
    "longTermInvestments": 1617000000,
    "taxAssets": 6256000000,
    "otherNonCurrentAssets": 14908000000,
    "totalNonCurrentAssets": 98126000000,
    "otherAssets": -1000000,
    "totalAssets": 127243000000,
    "totalPayables": 6247000000,
    "accountPayables": 4051000000,
    "otherPayables": 2196000000,
    "accruedExpenses": 3481000000,
    "shortTermDebt": 4760000000,
    "capitalLeaseObligationsCurrent": 874000000,
    "taxPayables": 2196000000,
    "deferredRevenue": 12032000000,
    "otherCurrentLiabilities": 4111000000,
    "totalCurrentLiabilities": 31505000000,
    "longTermDebt": 46025000000,
    "capitalLeaseObligationsNonCurrent": 2190000000,
    "deferredRevenueNonCurrent": 3499000000,
    "deferredTaxLiabilitiesNonCurrent": 2292000000,
    "otherNonCurrentLiabilities": 19711000000,
    "totalNonCurrentLiabilities": 73717000000,
    "otherLiabilities": 0,
    "capitalLeaseObligations": 3064000000,
    "totalLiabilities": 105222000000,
    "treasuryStock": -169484000000,
    "preferredStock": 0,
    "commonStock": 58343000000,
    "retainedEarnings": 149825000000,
    "additionalPaidInCapital": 0,
    "accumulatedOtherComprehensiveIncomeLoss": -16740000000,
    "otherTotalStockholdersEquity": 0,
    "totalStockholdersEquity": 21944000000,
    "totalEquity": 22021000000,
    "minorityInterest": 77000000,
    "totalLiabilitiesAndTotalEquity": 127243000000,
    "totalInvestments": 2469000000,
    "totalDebt": 54013000000,
    "netDebt": 46127000000
  },
  {
    "date": "2021-12-31",
    "symbol": "IBM",
    "reportedCurrency": "USD",
    "cik": "0000051143",
    "filingDate": "2022-02-22",
    "acceptedDate": "2022-02-22 16:07:29",
    "fiscalYear": "2021",
    "period": "FY",
    "cashAndCashEquivalents": 6650000000,
    "shortTermInvestments": 600000000,
    "cashAndShortTermInvestments": 7250000000,
    "netReceivables": 7225000000,
    "accountsReceivables": 6754000000,
    "otherReceivables": 471000000,
    "inventory": 1649000000,
    "prepaids": 1830000000,
    "otherCurrentAssets": 11585000000,
    "totalCurrentAssets": 29539000000,
    "propertyPlantEquipmentNet": 8916000000,
    "goodwill": 55643000000,
    "intangibleAssets": 12511000000,
    "goodwillAndIntangibleAssets": 68154000000,
    "longTermInvestments": 1823000000,
    "taxAssets": 7370000000,
    "otherNonCurrentAssets": 16199000000,
    "totalNonCurrentAssets": 102462000000,
    "otherAssets": 0,
    "totalAssets": 132001000000,
    "totalPayables": 6244000000,
    "accountPayables": 3955000000,
    "otherPayables": 2289000000,
    "accruedExpenses": 3204000000,
    "shortTermDebt": 6751000000,
    "capitalLeaseObligationsCurrent": 1010000000,
    "taxPayables": 2289000000,
    "deferredRevenue": 12518000000,
    "otherCurrentLiabilities": 3892000000,
    "totalCurrentLiabilities": 33619000000,
    "longTermDebt": 44917000000,
    "capitalLeaseObligationsNonCurrent": 2462000000,
    "deferredRevenueNonCurrent": 3577000000,
    "deferredTaxLiabilitiesNonCurrent": 3956000000,
    "otherNonCurrentLiabilities": 24474000000,
    "totalNonCurrentLiabilities": 79386000000,
    "otherLiabilities": 0,
    "capitalLeaseObligations": 3436000000,
    "totalLiabilities": 113005000000,
    "treasuryStock": -169392000000,
    "preferredStock": 0,
    "commonStock": 57319000000,
    "retainedEarnings": 154209000000,
    "additionalPaidInCapital": 0,
    "accumulatedOtherComprehensiveIncomeLoss": -23235000000,
    "otherTotalStockholdersEquity": 0,
    "totalStockholdersEquity": 18901000000,
    "totalEquity": 18996000000,
    "minorityInterest": 95000000,
    "totalLiabilitiesAndTotalEquity": 132001000000,
    "totalInvestments": 2423000000,
    "totalDebt": 55140000000,
    "netDebt": 48490000000
  },
  {
    "date": "2020-12-31",
    "symbol": "IBM",
    "reportedCurrency": "USD",
    "cik": "0000051143",
    "filingDate": "2021-02-23",
    "acceptedDate": "2021-02-23 17:08:23",
    "fiscalYear": "2020",
    "period": "FY",
    "cashAndCashEquivalents": 13212000000,
    "shortTermInvestments": 600000000,
    "cashAndShortTermInvestments": 13812000000,
    "netReceivables": 6215000000,
    "accountsReceivables": 5790000000,
    "otherReceivables": 425000000,
    "inventory": 1839000000,
    "prepaids": 1579000000,
    "otherCurrentAssets": 15771000000,
    "totalCurrentAssets": 39165000000,
    "propertyPlantEquipmentNet": 14726000000,
    "goodwill": 59617000000,
    "intangibleAssets": 13796000000,
    "goodwillAndIntangibleAssets": 73413000000,
    "longTermInvestments": 2282000000,
    "taxAssets": 9241000000,
    "otherNonCurrentAssets": 17145000000,
    "totalNonCurrentAssets": 116807000000,
    "otherAssets": -1000000,
    "totalAssets": 155971000000,
    "totalPayables": 4033000000,
    "accountPayables": 4033000000,
    "otherPayables": 0,
    "accruedExpenses": 7935000000,
    "shortTermDebt": 7116000000,
    "capitalLeaseObligationsCurrent": 1035000000,
    "taxPayables": 3301000000,
    "deferredRevenue": 12833000000,
    "otherCurrentLiabilities": 19750000000,
    "totalCurrentLiabilities": 39869000000,
    "longTermDebt": 54217000000,
    "capitalLeaseObligationsNonCurrent": 2780000000,
    "deferredRevenueNonCurrent": 4301000000,
    "deferredTaxLiabilitiesNonCurrent": 5472000000,
    "otherNonCurrentLiabilities": 38379000000,
    "totalNonCurrentLiabilities": 95376000000,
    "otherLiabilities": 0,
    "capitalLeaseObligations": 4931000000,
    "totalLiabilities": 135245000000,
    "treasuryStock": -169339000000,
    "preferredStock": 0,
    "commonStock": 56556000000,
    "retainedEarnings": 162717000000,
    "additionalPaidInCapital": 0,
    "accumulatedOtherComprehensiveIncomeLoss": -29337000000,
    "otherTotalStockholdersEquity": 0,
    "totalStockholdersEquity": 20597000000,
    "totalEquity": 20726000000,
    "minorityInterest": 129000000,
    "totalLiabilitiesAndTotalEquity": 155971000000,
    "totalInvestments": 816000000,
    "totalDebt": 65088000000,
    "netDebt": 51900000000
  }
]